pulsar_thread
