Metadata-Version: 2.1
Name: pulsar-thread
Version: 0.1.2
Summary: A connect pulsar message queue package, support multi-threaded production and consumption
Home-page: https://gitee.com/maxbanana/pulsar
Author: hongbo liu
Author-email: 782027465@qq.com
License: Apache
Platform: UNKNOWN
Classifier: Programming Language :: Python :: 3
Classifier: License :: OSI Approved :: Apache Software License
Classifier: Operating System :: OS Independent
Requires-Python: >=3.6
License-File: LICENSE
